Workbook
Name RMV: 'Parámetros'!$B$5
Name PctAsignacion: 'Parámetros'!$B$6
Name PctONP: 'Parámetros'!$B$7
Name PctEsSalud: 'Parámetros'!$B$8
Name DiasMes: 'Parámetros'!$B$9
Name HorasDia: 'Parámetros'!$B$10
Name Factor25: 'Parámetros'!$B$11
Name Factor35: 'Parámetros'!$B$12
Name TablaAFP: 'Parámetros'!$A$16:$D$20
Name ListaAFP: 'Parámetros'!$A$16:$A$20

Sheet Parámetros
A1: Parámetros
A2: Los parámetros no se escriben dentro de las fórmulas: están solo aquí y las fórmulas los usan por su nombre.
A4: Parámetro | B4: Valor | C4: Nombre en las fórmulas | D4: Fuente | E4: Fecha de consulta
A5: RMV (remuneración mínima vital) | B5: 1230 | C5: RMV | D5: D.S. N° 015-2026-TR (El Peruano, 28/09/2026), vigente desde el 1 de octubre de 2026 | E5: 29/10/2026
A6: Asignación familiar | B6: 0.1 | C6: PctAsignacion | D6: Ley 25129: 10% de la RMV (valor indicado en el enunciado) | E6: Enunciado
A7: ONP | B7: 0.13 | C7: PctONP | D7: D.L. 19990 (valor indicado en el enunciado) | E7: Enunciado
A8: EsSalud (lo paga el empleador) | B8: 0.09 | C8: PctEsSalud | D8: Ley 26790 (valor indicado en el enunciado) | E8: Enunciado
A9: Días del mes para el sueldo | B9: 30 | C9: DiasMes | D9: Regla del enunciado: sueldo ÷ 30 | E9: Enunciado
A10: Horas por día para el valor hora | B10: 8 | C10: HorasDia | D10: Regla del enunciado: sueldo ÷ 30 ÷ 8 | E10: Enunciado
A11: Recargo de horas extras al 25% | B11: 1.25 | C11: Factor25 | D11: Normas de jornada y sobretiempo (enunciado) | E11: Enunciado
A12: Recargo de horas extras al 35% | B12: 1.35 | C12: Factor35 | D12: Normas de jornada y sobretiempo (enunciado) | E12: Enunciado
A14: Tasas de cada AFP (sobre el total de remuneraciones)
A15: AFP | B15: Fondo | C15: Comisión | D15: Seguro | E15: Fuente | F15: Fecha de consulta
A16: AFP Ejemplo | B16: 0.1 | C16: 0.016 | D16: 0.0135 | E16: Valores de prueba del enunciado (solo para los casos 1 a 4) | F16: Enunciado
A17: Habitat | B17: 0.1 | C17: 0.0147 | D17: 0.0137 | E17: SBS, devengue octubre 2026 (comisión sobre flujo), publicado por Buk el 12/10/2026 | F17: 29/10/2026
A18: Integra | B18: 0.1 | C18: 0.0155 | D18: 0.0137 | E18: SBS, devengue octubre 2026 (comisión sobre flujo), publicado por Buk el 12/10/2026 | F18: 29/10/2026
A19: Prima | B19: 0.1 | C19: 0.016 | D19: 0.0137 | E19: SBS, devengue octubre 2026 (comisión sobre flujo), publicado por Buk el 12/10/2026 | F19: 29/10/2026
A20: Profuturo | B20: 0.1 | C20: 0.0169 | D20: 0.0137 | E20: SBS, devengue octubre 2026 (comisión sobre flujo), publicado por Buk el 12/10/2026 | F20: 29/10/2026
A22: Convención: cada concepto se redondea a 2 decimales y luego se suman. Montos en soles.

Sheet Boleta
A1: Boleta de ejemplo
A2: Cambia los datos en azul. Todo lo demás se calcula con fórmulas; la columna C muestra la fórmula de cada celda.
A4: Dato de entrada | B4: Valor | C4: Validación
A5: Sueldo básico (S/) | B5: 3000 | C5: =IF(AND(ISNUMBER(B5),B5>0),"OK","Debe ser mayor que cero")
A6: Días laborados | B6: 30 | C6: =IF(AND(ISNUMBER(B6),B6>=1,B6<=30,B6=INT(B6)),"OK","Entre 1 y 30")
A7: ¿Tiene hijos? (Sí / No) | B7: Sí | C7: =IF(OR(B7="Sí",B7="No"),"OK","Elegir Sí o No")
A8: Sistema de pensiones (ONP / AFP) | B8: AFP | C8: =IF(OR(B8="ONP",B8="AFP"),"OK","Elegir ONP o AFP")
A9: AFP (solo si eligió AFP) | B9: AFP Ejemplo | C9: =IF(B8="ONP","No aplica",IF(ISNA(MATCH(B9,ListaAFP,0)),"Elegir una AFP de la lista","OK"))
A10: Horas extras al 25% | B10: 4 | C10: =IF(AND(ISNUMBER(B10),B10>=0),"OK","Mayor o igual a cero")
A11: Horas extras al 35% | B11: 4 | C11: =IF(AND(ISNUMBER(B11),B11>=0),"OK","Mayor o igual a cero")
A12: Adelantos (S/) | B12: 200 | C12: =IF(AND(ISNUMBER(B12),B12>=0),"OK","Mayor o igual a cero")
A13: ¿Datos válidos? | B13: =IF(COUNTIF(C5:C12,"OK")+COUNTIF(C5:C12,"No aplica")=8,"Sí, se puede calcular","No: revisa la columna C")
A15: Concepto | B15: Monto (S/) | C15: Fórmula de la celda
A16: REMUNERACIONES
A17: Sueldo computable | B17: =ROUND(B5/DiasMes*B6,2) | C17: =_xlfn.FORMULATEXT(B17)
A18: Asignación familiar | B18: =IF(B7="Sí",ROUND(RMV*PctAsignacion,2),0) | C18: =_xlfn.FORMULATEXT(B18)
A19: Valor hora (no se redondea) | B19: =B5/DiasMes/HorasDia | C19: =_xlfn.FORMULATEXT(B19)
A20: Horas extras 25% | B20: =ROUND(B19*Factor25*B10,2) | C20: =_xlfn.FORMULATEXT(B20)
A21: Horas extras 35% | B21: =ROUND(B19*Factor35*B11,2) | C21: =_xlfn.FORMULATEXT(B21)
A22: Total remuneraciones | B22: =ROUND(SUM(B17,B18,B20,B21),2) | C22: =_xlfn.FORMULATEXT(B22)
A23: RETENCIONES / DESCUENTOS
A24: ONP | B24: =IF(B8="ONP",ROUND(B22*PctONP,2),0) | C24: =_xlfn.FORMULATEXT(B24)
A25: AFP fondo | B25: =IF(B8="AFP",ROUND(B22*VLOOKUP(B9,TablaAFP,2,FALSE),2),0) | C25: =_xlfn.FORMULATEXT(B25)
A26: AFP comisión | B26: =IF(B8="AFP",ROUND(B22*VLOOKUP(B9,TablaAFP,3,FALSE),2),0) | C26: =_xlfn.FORMULATEXT(B26)
A27: AFP seguro | B27: =IF(B8="AFP",ROUND(B22*VLOOKUP(B9,TablaAFP,4,FALSE),2),0) | C27: =_xlfn.FORMULATEXT(B27)
A28: Adelantos | B28: =ROUND(B12,2) | C28: =_xlfn.FORMULATEXT(B28)
A29: Total descuentos | B29: =ROUND(SUM(B24:B28),2) | C29: =_xlfn.FORMULATEXT(B29)
A30: NETO A PAGAR | B30: =ROUND(B22-B29,2) | C30: =_xlfn.FORMULATEXT(B30)
A31: APORTACIONES DEL EMPLEADOR
A32: EsSalud (9%) | B32: =ROUND(B22*PctEsSalud,2) | C32: =_xlfn.FORMULATEXT(B32)
A33: Costo total para el empleador | B33: =ROUND(B22+B32,2) | C33: =_xlfn.FORMULATEXT(B33)
A34: Neto como % del total de remuneraciones | B34: =B30/B22 | C34: =_xlfn.FORMULATEXT(B34)

Sheet Casos
A1: Casos de prueba y casos propios
A2: Mismas fórmulas que la hoja Boleta, una columna por caso. La app debe dar el mismo resultado, al centavo.
A4: Dato de entrada | B4: Caso 1 | C4: Caso 2 | D4: Caso 3 | E4: Caso 4 | F4: Propio 1 | G4: Propio 2
A5: Sueldo básico (S/) | B5: 2500 | C5: 1800 | D5: 3000 | E5: 4200 | F5: 2500 | G5: 4000
A6: Días laborados | B6: 30 | C6: 27 | D6: 30 | E6: 24 | F6: 30 | G6: 30
A7: ¿Tiene hijos? | B7: No | C7: Sí | D7: Sí | E7: Sí | F7: No | G7: No
A8: Sistema | B8: ONP | C8: ONP | D8: AFP | E8: AFP | F8: AFP | G8: ONP
A9: AFP | B9: AFP Ejemplo | C9: AFP Ejemplo | D9: AFP Ejemplo | E9: AFP Ejemplo | F9: Habitat | G9: AFP Ejemplo
A10: Horas extras 25% | B10: 0 | C10: 0 | D10: 4 | E10: 2 | F10: 0 | G10: 0
A11: Horas extras 35% | B11: 0 | C11: 0 | D11: 4 | E11: 2 | F11: 0 | G11: 0
A12: Adelantos (S/) | B12: 0 | C12: 0 | D12: 200 | E12: 100 | F12: 0 | G12: 0
A13: Cálculo | B13: Caso 1 | C13: Caso 2 | D13: Caso 3 | E13: Caso 4 | F13: Propio 1 | G13: Propio 2
A14: Sueldo computable | B14: =ROUND(B5/DiasMes*B6,2) | C14: =ROUND(C5/DiasMes*C6,2) | D14: =ROUND(D5/DiasMes*D6,2) | E14: =ROUND(E5/DiasMes*E6,2) | F14: =ROUND(F5/DiasMes*F6,2) | G14: =ROUND(G5/DiasMes*G6,2)
A15: Asignación familiar | B15: =IF(B7="Sí",ROUND(RMV*PctAsignacion,2),0) | C15: =IF(C7="Sí",ROUND(RMV*PctAsignacion,2),0) | D15: =IF(D7="Sí",ROUND(RMV*PctAsignacion,2),0) | E15: =IF(E7="Sí",ROUND(RMV*PctAsignacion,2),0) | F15: =IF(F7="Sí",ROUND(RMV*PctAsignacion,2),0) | G15: =IF(G7="Sí",ROUND(RMV*PctAsignacion,2),0)
A16: Valor hora | B16: =B5/DiasMes/HorasDia | C16: =C5/DiasMes/HorasDia | D16: =D5/DiasMes/HorasDia | E16: =E5/DiasMes/HorasDia | F16: =F5/DiasMes/HorasDia | G16: =G5/DiasMes/HorasDia
A17: Horas extras 25% | B17: =ROUND(B16*Factor25*B10,2) | C17: =ROUND(C16*Factor25*C10,2) | D17: =ROUND(D16*Factor25*D10,2) | E17: =ROUND(E16*Factor25*E10,2) | F17: =ROUND(F16*Factor25*F10,2) | G17: =ROUND(G16*Factor25*G10,2)
A18: Horas extras 35% | B18: =ROUND(B16*Factor35*B11,2) | C18: =ROUND(C16*Factor35*C11,2) | D18: =ROUND(D16*Factor35*D11,2) | E18: =ROUND(E16*Factor35*E11,2) | F18: =ROUND(F16*Factor35*F11,2) | G18: =ROUND(G16*Factor35*G11,2)
A19: Total remuneraciones | B19: =ROUND(SUM(B14,B15,B17,B18),2) | C19: =ROUND(SUM(C14,C15,C17,C18),2) | D19: =ROUND(SUM(D14,D15,D17,D18),2) | E19: =ROUND(SUM(E14,E15,E17,E18),2) | F19: =ROUND(SUM(F14,F15,F17,F18),2) | G19: =ROUND(SUM(G14,G15,G17,G18),2)
A20: ONP | B20: =IF(B8="ONP",ROUND(B19*PctONP,2),0) | C20: =IF(C8="ONP",ROUND(C19*PctONP,2),0) | D20: =IF(D8="ONP",ROUND(D19*PctONP,2),0) | E20: =IF(E8="ONP",ROUND(E19*PctONP,2),0) | F20: =IF(F8="ONP",ROUND(F19*PctONP,2),0) | G20: =IF(G8="ONP",ROUND(G19*PctONP,2),0)
A21: AFP fondo | B21: =IF(B8="AFP",ROUND(B19*VLOOKUP(B9,TablaAFP,2,FALSE),2),0) | C21: =IF(C8="AFP",ROUND(C19*VLOOKUP(C9,TablaAFP,2,FALSE),2),0) | D21: =IF(D8="AFP",ROUND(D19*VLOOKUP(D9,TablaAFP,2,FALSE),2),0) | E21: =IF(E8="AFP",ROUND(E19*VLOOKUP(E9,TablaAFP,2,FALSE),2),0) | F21: =IF(F8="AFP",ROUND(F19*VLOOKUP(F9,TablaAFP,2,FALSE),2),0) | G21: =IF(G8="AFP",ROUND(G19*VLOOKUP(G9,TablaAFP,2,FALSE),2),0)
A22: AFP comisión | B22: =IF(B8="AFP",ROUND(B19*VLOOKUP(B9,TablaAFP,3,FALSE),2),0) | C22: =IF(C8="AFP",ROUND(C19*VLOOKUP(C9,TablaAFP,3,FALSE),2),0) | D22: =IF(D8="AFP",ROUND(D19*VLOOKUP(D9,TablaAFP,3,FALSE),2),0) | E22: =IF(E8="AFP",ROUND(E19*VLOOKUP(E9,TablaAFP,3,FALSE),2),0) | F22: =IF(F8="AFP",ROUND(F19*VLOOKUP(F9,TablaAFP,3,FALSE),2),0) | G22: =IF(G8="AFP",ROUND(G19*VLOOKUP(G9,TablaAFP,3,FALSE),2),0)
A23: AFP seguro | B23: =IF(B8="AFP",ROUND(B19*VLOOKUP(B9,TablaAFP,4,FALSE),2),0) | C23: =IF(C8="AFP",ROUND(C19*VLOOKUP(C9,TablaAFP,4,FALSE),2),0) | D23: =IF(D8="AFP",ROUND(D19*VLOOKUP(D9,TablaAFP,4,FALSE),2),0) | E23: =IF(E8="AFP",ROUND(E19*VLOOKUP(E9,TablaAFP,4,FALSE),2),0) | F23: =IF(F8="AFP",ROUND(F19*VLOOKUP(F9,TablaAFP,4,FALSE),2),0) | G23: =IF(G8="AFP",ROUND(G19*VLOOKUP(G9,TablaAFP,4,FALSE),2),0)
A24: Adelantos | B24: =ROUND(B12,2) | C24: =ROUND(C12,2) | D24: =ROUND(D12,2) | E24: =ROUND(E12,2) | F24: =ROUND(F12,2) | G24: =ROUND(G12,2)
A25: Total descuentos | B25: =ROUND(SUM(B20:B24),2) | C25: =ROUND(SUM(C20:C24),2) | D25: =ROUND(SUM(D20:D24),2) | E25: =ROUND(SUM(E20:E24),2) | F25: =ROUND(SUM(F20:F24),2) | G25: =ROUND(SUM(G20:G24),2)
A26: NETO A PAGAR | B26: =ROUND(B19-B25,2) | C26: =ROUND(C19-C25,2) | D26: =ROUND(D19-D25,2) | E26: =ROUND(E19-E25,2) | F26: =ROUND(F19-F25,2) | G26: =ROUND(G19-G25,2)
A27: EsSalud (9%) | B27: =ROUND(B19*PctEsSalud,2) | C27: =ROUND(C19*PctEsSalud,2) | D27: =ROUND(D19*PctEsSalud,2) | E27: =ROUND(E19*PctEsSalud,2) | F27: =ROUND(F19*PctEsSalud,2) | G27: =ROUND(G19*PctEsSalud,2)
A28: Costo total para el empleador | B28: =ROUND(B19+B27,2) | C28: =ROUND(C19+C27,2) | D28: =ROUND(D19+D27,2) | E28: =ROUND(E19+E27,2) | F28: =ROUND(F19+F27,2) | G28: =ROUND(G19+G27,2)
A29: Neto como % del total de remuneraciones | B29: =B26/B19 | C29: =C26/C19 | D29: =D26/D19 | E29: =E26/E19 | F29: =F26/F19 | G29: =G26/G19
A31: Control cruzado | B31: Caso 1 | C31: Caso 2 | D31: Caso 3 | E31: Caso 4 | F31: Propio 1 | G31: Propio 2
A32: Neto según el documento | B32: 2175 | C32: 1516.41 | D32: 2631.73 | E32: Lo revisa el docente | F32: Sin respuesta | G32: Sin respuesta
A33: Diferencia (Excel − documento) | B33: =ROUND(B26-B32,2) | C33: =ROUND(C26-C32,2) | D33: =ROUND(D26-D32,2) | E33: — | F33: — | G33: —
A34: ¿Coincide al centavo? | B34: =IF(B33=0,"Sí","No") | C34: =IF(C33=0,"Sí","No") | D34: =IF(D33=0,"Sí","No") | E34: — | F34: — | G34: —
A36: Casos propios: datos reales | B36: Puesto | C36: Entidad | D36: Sueldo publicado | E36: Enlace | F36: Fecha de consulta
A37: Propio 1 | B37: Asistente de Programación | C37: SUNARP, Zona Registral N° IX (CAS N° 061) | D37: 2500 | E37: https://www.convocatoriasdetrabajo.com/oportunidad-laboral-cas-061-asistente-programacion-sunarp-lima-635723.html | F37: 29/10/2026
A38: Propio 2 | B38: Analista de Sistemas | C38: SUNARP, Zona Registral N° IX (CAS N° 061) | D38: 4000 | E38: https://www.convocatoriasdetrabajo.com/oportunidad-laboral-cas-061-analista-sistemas-sunarp-lima-635724.html | F38: 29/10/2026
A39: Bases oficiales: https://www.gob.pe/institucion/sunarp/informes-publicaciones/8667351-proceso-cas-n-061-2025-sunarp-zona-registral-n-ix
A40: Solo el sueldo es real. Los demás datos (días, hijos, sistema de pensiones) son ficticios, como pide el enunciado.

Sheet Explicación
A1: Explicación de cada fórmula
A2: Para alguien que no sabe contabilidad. El ejemplo numérico usa el caso 3 (S/ 3,000, 30 días, con hijos, AFP Ejemplo, 4 h al 25%, 4 h al 35%, adelanto S/ 200), que es el que está cargado en la hoja Boleta.
A4: Concepto | B4: Qué es | C4: Cómo se calcula (en palabras) | D4: Fórmula en Excel (hoja Boleta) | E4: Ejemplo numérico | F4: Resultado en la hoja Boleta
A5: Sueldo computable | B5: La parte del sueldo que corresponde a los días que realmente trabajó. | C5: Sueldo básico ÷ 30 × días laborados | D5: =_xlfn.FORMULATEXT(Boleta!B17) | E5: 3,000 ÷ 30 × 30 = 3,000.00 | F5: =Boleta!B17
A6: Asignación familiar | B6: Un monto fijo para quien tiene hijos. No se recorta por días. | C6: Si tiene hijos: 10% de la RMV. Si no: 0 | D6: =_xlfn.FORMULATEXT(Boleta!B18) | E6: 10% × 1,230 = 123.00 | F6: =Boleta!B18
A7: Valor hora | B7: Cuánto vale una hora normal de trabajo. Sirve para pagar las horas extras. | C7: Sueldo básico ÷ 30 ÷ 8 | D7: =_xlfn.FORMULATEXT(Boleta!B19) | E7: 3,000 ÷ 30 ÷ 8 = 12.50 | F7: =Boleta!B19
A8: Horas extras 25% | B8: Las primeras horas extra se pagan 25% más caras que una hora normal. | C8: Valor hora × 1.25 × número de horas | D8: =_xlfn.FORMULATEXT(Boleta!B20) | E8: 12.50 × 1.25 × 4 = 62.50 | F8: =Boleta!B20
A9: Horas extras 35% | B9: Las horas extra siguientes se pagan 35% más caras. | C9: Valor hora × 1.35 × número de horas | D9: =_xlfn.FORMULATEXT(Boleta!B21) | E9: 12.50 × 1.35 × 4 = 67.50 | F9: =Boleta!B21
A10: Total remuneraciones | B10: Todo lo que gana el trabajador en el mes, antes de descuentos (sueldo bruto). | C10: Suma de sueldo computable, asignación familiar y horas extras | D10: =_xlfn.FORMULATEXT(Boleta!B22) | E10: 3,000 + 123 + 62.50 + 67.50 = 3,253.00 | F10: =Boleta!B22
A11: ONP | B11: Aporte a la pensión del Estado. Solo se descuenta si está en la ONP. | C11: 13% del total de remuneraciones | D11: =_xlfn.FORMULATEXT(Boleta!B24) | E11: No aplica en el caso 3 (está en AFP) = 0.00 | F11: =Boleta!B24
A12: AFP fondo | B12: La parte que se ahorra en la cuenta personal de jubilación del trabajador. | C12: Tasa de fondo de su AFP × total de remuneraciones | D12: =_xlfn.FORMULATEXT(Boleta!B25) | E12: 10% × 3,253 = 325.30 | F12: =Boleta!B25
A13: AFP comisión | B13: Lo que la AFP cobra por administrar ese ahorro. | C13: Tasa de comisión de su AFP × total de remuneraciones | D13: =_xlfn.FORMULATEXT(Boleta!B26) | E13: 1.6% × 3,253 = 52.048 → 52.05 | F13: =Boleta!B26
A14: AFP seguro | B14: Seguro que cubre invalidez o fallecimiento. | C14: Tasa de seguro de su AFP × total de remuneraciones | D14: =_xlfn.FORMULATEXT(Boleta!B27) | E14: 1.35% × 3,253 = 43.9155 → 43.92 | F14: =Boleta!B27
A15: Adelantos | B15: Dinero que el trabajador ya recibió antes de fin de mes; se le resta. | C15: Se resta el monto tal cual | D15: =_xlfn.FORMULATEXT(Boleta!B28) | E15: 200.00 | F15: =Boleta!B28
A16: Total descuentos | B16: Todo lo que se le quita al trabajador. | C16: Pensión (ONP o AFP) + adelantos | D16: =_xlfn.FORMULATEXT(Boleta!B29) | E16: 325.30 + 52.05 + 43.92 + 200 = 621.27 | F16: =Boleta!B29
A17: NETO A PAGAR | B17: Lo que de verdad llega a la cuenta del trabajador. | C17: Total remuneraciones − total descuentos | D17: =_xlfn.FORMULATEXT(Boleta!B30) | E17: 3,253.00 − 621.27 = 2,631.73 | F17: =Boleta!B30
A18: EsSalud | B18: Seguro de salud que paga la empresa. No se descuenta al trabajador. | C18: 9% del total de remuneraciones | D18: =_xlfn.FORMULATEXT(Boleta!B32) | E18: 9% × 3,253 = 292.77 | F18: =Boleta!B32
A19: Costo total para el empleador | B19: Lo que la empresa gasta en ese trabajador ese mes. | C19: Total remuneraciones + EsSalud | D19: =_xlfn.FORMULATEXT(Boleta!B33) | E19: 3,253.00 + 292.77 = 3,545.77 | F19: =Boleta!B33
A21: Regla de redondeo | B21: Cada concepto se redondea a 2 decimales con ROUND y después se suman. Así el Excel y la app dan el mismo resultado al centavo.
A22: Parámetros | B22: RMV, porcentajes y tasas de AFP no están escritos en las fórmulas: se leen de la hoja Parámetros por su nombre (RMV, PctONP, TablaAFP...).
